restapi3/__init__.py
restapi3/api.py
restapi3/method.py
restapi3-0.0.1.dist-info/DESCRIPTION.rst
restapi3-0.0.1.dist-info/METADATA
restapi3-0.0.1.dist-info/RECORD
restapi3-0.0.1.dist-info/WHEEL
restapi3-0.0.1.dist-info/metadata.json
restapi3-0.0.1.dist-info/top_level.txt
