Metadata-Version: 2.0
Name: restapi3
Version: 0.0.1
Summary: Formatted APIs presentation for testing.
Home-page: https://github.com/imaging8896/restapi3
Author: imaging8896
Author-email: imaging8896@gmail.com
License: UNKNOWN
Platform: UNKNOWN
Classifier: Programming Language :: Python :: 3
Classifier: License :: OSI Approved :: MIT License
Classifier: Operating System :: OS Independent
Requires-Dist: setuptools
Requires-Dist: requests
